{
    "den-andra-typen-av-forsvarsminister-minister": {
        "title": "Den-andra-typen-av-försvarsminister-minister",
        "name": "Arvid",
        "description": ""
    },
    "finansminister": {
        "title": "Finansminister",
        "name": "Arvid",
        "description": ""
    },
    "utbildningsminister": {
        "title": "Utbildningsminister",
        "name": "A.J. Öhman",
        "description": ""
    },
    "industriminister": {
        "title": "Industriminister",
        "name": "Axel Thornberg",
        "description": ""
    },
    "citatminister": {
        "title": "Citatminister",
        "name": "Emil S. Winroth",
        "description": ""
    },
    "transportminister": {
        "title": "Transportminister",
        "name": "Viggo S.E.S.",
        "description": "Transportministern ansvarar för allt inom transport. Från tåg till pirror."
    },
    "ordinarieutrikesminister": {
        "title": "Ordinarieutrikesminister",
        "name": "A.J. Öhman",
        "description": ""
    },
    "suppleantutrikesminister": {
        "title": "Suppleantutrikesminister",
        "name": "Viggo S.E.S.",
        "description": ""
    },
    "lag-%20och-%20rattminister": {
        "title": "Lag- och Rättminister",
        "name": "Emil S. Winroth",
        "description": ""
    },
    "domstolsminister": {
        "title": "Domstolsminister",
        "name": "A.J. Öhman",
        "description": ""
    },
    "befolkningsminister": {
        "title": "Befolkningsminister",
        "name": "L. Emil A.",
        "description": ""
    },
    "under-y-63-byggminister": {
        "title": "Under-y-63-byggminister",
        "name": "Viggo S.E.S.",
        "description": ""
    },
    "den-%20ena-%20broministern": {
        "title": "Den ena broministern",
        "name": "Viggo S.E.S.",
        "description": ""
    },
    "forsvarsminister": {
        "title": "Försvarsminister",
        "name": "Emil S. Winroth",
        "description": ""
    },
    "jordbruksminister": {
        "title": "Jordbruksminister",
        "name": "Viggo S.E.S.",
        "description": ""
    },
    "sjukvardsminister": {
        "title": "Sjukvårdsminister",
        "name": "Emil S. Winroth",
        "description": ""
    },
    "bokminister": {
        "title": "Bokminister",
        "name": "L. Emil A.",
        "description": ""
    },
    "hastminister": {
        "title": "Hästminister",
        "name": "A.J. Öhman",
        "description": ""
    },
    "tagminister": {
        "title": "Tågminister",
        "name": "L. Emil A.",
        "description": ""
    },
    "musikminister": {
        "title": "Musikminister",
        "name": "Axel Thornberg",
        "description": ""
    },
    "metalminister": {
        "title": "Metalminister",
        "name": "Axel Thornberg",
        "description": ""
    },
    "ministerminister": {
        "title": "Ministerminister",
        "name": "Axel Thornberg",
        "description": ""
    },
    "inredningsminister": {
        "title": "Inredningsminister",
        "name": "A.J. Öhman",
        "description": ""
    },
    "flygminister": {
        "title": "Flygminister",
        "name": "L. Emil A.",
        "description": ""
    },
    "den-%20andra-%20broministern": {
        "title": "Den andra broministern",
        "name": "L. Emil A.",
        "description": ""
    },
    "humorminister": {
        "title": "Humorminister",
        "name": "L. Emil A.",
        "description": ""
    },
    "swiftminister": {
        "title": "Swiftminister",
        "name": "A.J. Öhman",
        "description": ""
    },
    "ravminister": {
        "title": "Rävminister",
        "name": "Axel Thornberg",
        "description": ""
    },
    "ek-minister": {
        "title": "EK-minister",
        "name": "L. Emil A.",
        "description": ""
    },
    "modminister": {
        "title": "Modminister",
        "name": "Axel Thornberg",
        "description": ""
    },
    "schaktminister": {
        "title": "Schaktminister",
        "name": "Viggo S.E.S.",
        "description": ""
    },
    "hissminister": {
        "title": "Hissminister",
        "name": "L. Emil A.",
        "description": ""
    },
    "sakerhetsminister": {
        "title": "Säkerhetsminister",
        "name": "A.J. Öhman",
        "description": ""
    },
    "osakerhetsminister": {
        "title": "Osäkerhetsminister",
        "name": "Viggo S.E.S.",
        "description": ""
    },
    "%22musik%22-minister": {
        "title": "\"Musik\"minister",
        "name": "Emil S. Winroth",
        "description": ""
    },
    "kistminister": {
        "title": "Kistminister",
        "name": "Viggo S.E.S.",
        "description": ""
    },
    "geogissningsminister": {
        "title": "Geogissningsminister",
        "name": "Axel Thornberg",
        "description": ""
    },
    "odenminister": {
        "title": "Odenminister",
        "name": "Axel Thornberg",
        "description": ""
    },
    "torminister": {
        "title": "Torminister",
        "name": "Axel Thornberg",
        "description": ""
    },
    "lokeminister": {
        "title": "Lokeminister",
        "name": "Arvid",
        "description": ""
    },
    "idunminister": {
        "title": "Idunminister",
        "name": "L. Emil A.",
        "description": ""
    },
    "hustomtsminister": {
        "title": "Hustomtsminister",
        "name": "Emil S. Winroth",
        "description": ""
    },
    "mattminister": {
        "title": "Mattminister",
        "name": "Viggo S.E.S.",
        "description": ""
    },
    "pythonminister": {
        "title": "Pythonminister",
        "name": "Axel Thornberg",
        "description": ""
    },
    "javascriptminister": {
        "title": "Javascriptminister",
        "name": "Viggo S.E.S.",
        "description": ""
    },
    "typescriptminister": {
        "title": "Typescriptminister",
        "name": "Emil S. Winroth",
        "description": ""
    },
    "oppositionsminister": {
        "title": "Oppositionsminister",
        "name": "Viggo S.E.S.",
        "description": ""
    },
    "vice-oppositionsminister": {
        "title": "Vice-Oppositionsminister",
        "name": "Emil S. Winroth",
        "description": ""
    },
    "vice-vice-oppositionsminister-minister": {
        "title": "Vice-Vice-Oppositionsminister-minister",
        "name": "L. Emil A.",
        "description": ""
    },
    "personlighetsminister": {
        "title": "Personlighetsminister",
        "name": "A.J. Öhman",
        "description": ""
    },
    "tagluffarminister": {
        "title": "Tågluffarminister",
        "name": "Emil S. Winroth",
        "description": ""
    },
    "redaktionsminister": {
        "title": "Redaktionsminister",
        "name": "Emil S. Winroth",
        "description": ""
    },
    "norgeminister": {
        "title": "Norgeminister",
        "name": "Emil S. Winroth",
        "description": ""
    },
    "danmarksminister": {
        "title": "Danmarksminister",
        "name": "A.J. Öhman",
        "description": ""
    },
    "mellanosternminister": {
        "title": "Mellanösternminister",
        "name": "Viggo S.E.S.",
        "description": ""
    },
    "sparvagnsminister": {
        "title": "Spårvagnsminister",
        "name": "L. Emil A.",
        "description": ""
    },
    "ovrigtminister": {
        "title": "Övrigtminister",
        "name": "Emil S. Winroth",
        "description": ""
    }
}